nucypher_ipfs/__init__.py
nucypher_ipfs/client.py
nucypher_ipfs-0.0.5.dist-info/LICENSE
nucypher_ipfs-0.0.5.dist-info/METADATA
nucypher_ipfs-0.0.5.dist-info/WHEEL
nucypher_ipfs-0.0.5.dist-info/top_level.txt
nucypher_ipfs-0.0.5.dist-info/RECORD
