Metadata-Version: 2.1
Name: nucypher-ipfs
Version: 0.0.5
Summary: Python SDK allows python developers to securely upload and download a file to IPFS, end-to-end encrypting data with keys from NuCypher network
Home-page: https://github.com/pisuthd/nucypher-ipfs
Author: Pisuth D.
Author-email: pisuth.dae@gmail.com
License: UNKNOWN
Platform: UNKNOWN
Classifier: Programming Language :: Python :: 3
Classifier: License :: OSI Approved :: MIT License
Classifier: Operating System :: OS Independent
Requires-Dist: ipfsapi
Requires-Dist: nucypher
Requires-Dist: Faker
